{
    "dataType": "Constellation",
    "ark": "http:\/\/n2t.net\/ark:\/99166\/w6tg0kqj",
    "entityType": {
        "id": "698",
        "term": "corporateBody",
        "uri": "http:\/\/socialarchive.iath.virginia.edu\/control\/term#CorporateBody",
        "type": "entity_type"
    },
    "entityIDs": [
        {
            "dataType": "EntityId",
            "type": {
                "id": "703",
                "term": "MARCOrg",
                "type": "entityid_type"
            },
            "text": "CoCF",
            "id": "76764956",
            "version": "11225849"
        },
        {
            "dataType": "EntityId",
            "type": {
                "id": "400255",
                "term": "OCLC ID",
                "type": "entityid_type",
                "description": "OCLC Numeric Identifier"
            },
            "text": "47828",
            "id": "76764957",
            "version": "11225849"
        }
    ],
    "maintenanceStatus": {
        "term": "revised"
    },
    "maintenanceAgency": "SNAC: Social Networks and Archival Context",
    "maintenanceEvents": [
        {
            "dataType": "MaintenanceEvent",
            "eventType": {
                "id": "704",
                "term": "revised",
                "type": "event_type"
            },
            "eventDateTime": "2016-11-22T11:29:01",
            "standardDateTime": "2016-11-22T11:29:01",
            "agentType": {
                "id": "400254",
                "term": "human",
                "type": "agent_type"
            },
            "agent": "System Service (system@localhost)",
            "eventDescription": "User published constellation"
        }
    ],
    "nameEntries": [
        {
            "dataType": "NameEntry",
            "original": "Colorado Springs Fine Arts Center",
            "preferenceScore": "99",
            "components": [
                {
                    "dataType": "NameComponent",
                    "text": "Colorado Springs Fine Arts Center",
                    "order": "0",
                    "type": {
                        "id": "400228",
                        "term": "Name",
                        "type": "name_component"
                    },
                    "id": "76764955",
                    "version": "11225849"
                }
            ],
            "id": "76764954",
            "version": "11225849"
        }
    ],
    "relations": [
        {
            "dataType": "ConstellationRelation",
            "sourceConstellation": "76764953",
            "targetConstellation": "44536188",
            "sourceArkID": "http:\/\/n2t.net\/ark:\/99166\/w6tg0kqj",
            "targetArkID": "http:\/\/n2t.net\/ark:\/99166\/w6x11bfw",
            "targetEntityType": {
                "id": "698",
                "term": "corporateBody",
                "uri": "http:\/\/socialarchive.iath.virginia.edu\/control\/term#CorporateBody",
                "type": "entity_type"
            },
            "type": {
                "term": "mayBeSameAs",
                "type": "relation_type"
            },
            "content": "Colorado Springs Fine Arts Center"
        }
    ],
    "places": [
        {
            "dataType": "Place",
            "original": "Colorado Springs Fine Arts Center",
            "type": {
                "id": "400242",
                "term": "Address",
                "uri": "http:\/\/socialarchive.iath.virginia.edu\/control\/term#Address",
                "type": "place_type"
            },
            "address": [
                {
                    "dataType": "AddressLine",
                    "text": "Library",
                    "order": "0",
                    "type": {
                        "id": "400243",
                        "term": "Unspecified",
                        "uri": "http:\/\/socialarchive.iath.virginia.edu\/control\/term#Unspecified",
                        "type": "address_part"
                    },
                    "id": "76764959",
                    "version": "11225849"
                },
                {
                    "dataType": "AddressLine",
                    "text": "30 W Dale St",
                    "order": "1",
                    "type": {
                        "id": "400243",
                        "term": "Unspecified",
                        "uri": "http:\/\/socialarchive.iath.virginia.edu\/control\/term#Unspecified",
                        "type": "address_part"
                    },
                    "id": "76764960",
                    "version": "11225849"
                },
                {
                    "dataType": "AddressLine",
                    "text": "Colorado Springs",
                    "order": "2",
                    "type": {
                        "id": "400243",
                        "term": "Unspecified",
                        "uri": "http:\/\/socialarchive.iath.virginia.edu\/control\/term#Unspecified",
                        "type": "address_part"
                    },
                    "id": "76764961",
                    "version": "11225849"
                },
                {
                    "dataType": "AddressLine",
                    "text": "US-CO",
                    "order": "3",
                    "type": {
                        "id": "400243",
                        "term": "Unspecified",
                        "uri": "http:\/\/socialarchive.iath.virginia.edu\/control\/term#Unspecified",
                        "type": "address_part"
                    },
                    "id": "76764962",
                    "version": "11225849"
                },
                {
                    "dataType": "AddressLine",
                    "text": "80903-3249",
                    "order": "4",
                    "type": {
                        "id": "400243",
                        "term": "Unspecified",
                        "uri": "http:\/\/socialarchive.iath.virginia.edu\/control\/term#Unspecified",
                        "type": "address_part"
                    },
                    "id": "76764963",
                    "version": "11225849"
                },
                {
                    "dataType": "AddressLine",
                    "text": "US",
                    "order": "5",
                    "type": {
                        "id": "400243",
                        "term": "Unspecified",
                        "uri": "http:\/\/socialarchive.iath.virginia.edu\/control\/term#Unspecified",
                        "type": "address_part"
                    },
                    "id": "76764964",
                    "version": "11225849"
                }
            ],
            "geoplace": {
                "id": "15333",
                "name": "Colorado Springs Fine Arts Center",
                "latitude": "38.8358000",
                "longitude": "-104.8180000"
            },
            "confirmed": true,
            "id": "76764958",
            "version": "11225849"
        }
    ],
    "id": "76764953",
    "version": "11225852"
}