{
    "dataType": "Constellation",
    "ark": "http:\/\/n2t.net\/ark:\/99166\/w6ps8j9n",
    "entityType": {
        "id": "698",
        "term": "corporateBody",
        "uri": "http:\/\/socialarchive.iath.virginia.edu\/control\/term#CorporateBody",
        "type": "entity_type"
    },
    "entityIDs": [
        {
            "dataType": "EntityId",
            "type": {
                "id": "703",
                "term": "MARCOrg",
                "type": "entityid_type"
            },
            "text": "PBa",
            "id": "76762702",
            "version": "11225017"
        },
        {
            "dataType": "EntityId",
            "type": {
                "id": "400255",
                "term": "OCLC ID",
                "type": "entityid_type",
                "description": "OCLC Numeric Identifier"
            },
            "text": "4927",
            "id": "76762703",
            "version": "11225017"
        }
    ],
    "maintenanceStatus": {
        "term": "revised"
    },
    "maintenanceAgency": "SNAC: Social Networks and Archival Context",
    "maintenanceEvents": [
        {
            "dataType": "MaintenanceEvent",
            "eventType": {
                "id": "704",
                "term": "revised",
                "type": "event_type"
            },
            "eventDateTime": "2016-11-22T11:27:09",
            "standardDateTime": "2016-11-22T11:27:09",
            "agentType": {
                "id": "400254",
                "term": "human",
                "type": "agent_type"
            },
            "agent": "System Service (system@localhost)",
            "eventDescription": "User published constellation"
        }
    ],
    "nameEntries": [
        {
            "dataType": "NameEntry",
            "original": "Bryn Athyn College, Swedenborg Library",
            "preferenceScore": "99",
            "components": [
                {
                    "dataType": "NameComponent",
                    "text": "Bryn Athyn College, Swedenborg Library",
                    "order": "0",
                    "type": {
                        "id": "400228",
                        "term": "Name",
                        "type": "name_component"
                    },
                    "id": "76762701",
                    "version": "11225017"
                }
            ],
            "id": "76762700",
            "version": "11225017"
        }
    ],
    "places": [
        {
            "dataType": "Place",
            "original": "Bryn Athyn College, Swedenborg Library",
            "type": {
                "id": "400242",
                "term": "Address",
                "uri": "http:\/\/socialarchive.iath.virginia.edu\/control\/term#Address",
                "type": "place_type"
            },
            "address": [
                {
                    "dataType": "AddressLine",
                    "text": "2925 College Drive",
                    "order": "0",
                    "type": {
                        "id": "400243",
                        "term": "Unspecified",
                        "uri": "http:\/\/socialarchive.iath.virginia.edu\/control\/term#Unspecified",
                        "type": "address_part"
                    },
                    "id": "76762705",
                    "version": "11225017"
                },
                {
                    "dataType": "AddressLine",
                    "text": "Bryn Athyn",
                    "order": "1",
                    "type": {
                        "id": "400243",
                        "term": "Unspecified",
                        "uri": "http:\/\/socialarchive.iath.virginia.edu\/control\/term#Unspecified",
                        "type": "address_part"
                    },
                    "id": "76762706",
                    "version": "11225017"
                },
                {
                    "dataType": "AddressLine",
                    "text": "US-PA",
                    "order": "2",
                    "type": {
                        "id": "400243",
                        "term": "Unspecified",
                        "uri": "http:\/\/socialarchive.iath.virginia.edu\/control\/term#Unspecified",
                        "type": "address_part"
                    },
                    "id": "76762707",
                    "version": "11225017"
                },
                {
                    "dataType": "AddressLine",
                    "text": "19009-0740",
                    "order": "3",
                    "type": {
                        "id": "400243",
                        "term": "Unspecified",
                        "uri": "http:\/\/socialarchive.iath.virginia.edu\/control\/term#Unspecified",
                        "type": "address_part"
                    },
                    "id": "76762708",
                    "version": "11225017"
                },
                {
                    "dataType": "AddressLine",
                    "text": "US",
                    "order": "4",
                    "type": {
                        "id": "400243",
                        "term": "Unspecified",
                        "uri": "http:\/\/socialarchive.iath.virginia.edu\/control\/term#Unspecified",
                        "type": "address_part"
                    },
                    "id": "76762709",
                    "version": "11225017"
                }
            ],
            "geoplace": {
                "id": "15253",
                "name": "Bryn Athyn College, Swedenborg Library",
                "latitude": "40.1343000",
                "longitude": "-75.0608000"
            },
            "confirmed": true,
            "id": "76762704",
            "version": "11225017"
        }
    ],
    "id": "76762699",
    "version": "11225020"
}