{
    "dataType": "Constellation",
    "ark": "http:\/\/n2t.net\/ark:\/99166\/w6b38htz",
    "entityType": {
        "id": "698",
        "term": "corporateBody",
        "uri": "http:\/\/socialarchive.iath.virginia.edu\/control\/term#CorporateBody",
        "type": "entity_type"
    },
    "entityIDs": [
        {
            "dataType": "EntityId",
            "type": {
                "id": "703",
                "term": "MARCOrg",
                "type": "entityid_type"
            },
            "text": "INap",
            "id": "76775986",
            "version": "11230013"
        },
        {
            "dataType": "EntityId",
            "type": {
                "id": "400255",
                "term": "OCLC ID",
                "type": "entityid_type",
                "description": "OCLC Numeric Identifier"
            },
            "text": "10075",
            "id": "76775987",
            "version": "11230013"
        }
    ],
    "maintenanceStatus": {
        "term": "revised"
    },
    "maintenanceAgency": "SNAC: Social Networks and Archival Context",
    "maintenanceEvents": [
        {
            "dataType": "MaintenanceEvent",
            "eventType": {
                "id": "704",
                "term": "revised",
                "type": "event_type"
            },
            "eventDateTime": "2016-11-22T11:38:25",
            "standardDateTime": "2016-11-22T11:38:25",
            "agentType": {
                "id": "400254",
                "term": "human",
                "type": "agent_type"
            },
            "agent": "System Service (system@localhost)",
            "eventDescription": "User published constellation"
        }
    ],
    "nameEntries": [
        {
            "dataType": "NameEntry",
            "original": "Naperville Public Library",
            "preferenceScore": "99",
            "components": [
                {
                    "dataType": "NameComponent",
                    "text": "Naperville Public Library",
                    "order": "0",
                    "type": {
                        "id": "400228",
                        "term": "Name",
                        "type": "name_component"
                    },
                    "id": "76775985",
                    "version": "11230013"
                }
            ],
            "id": "76775984",
            "version": "11230013"
        }
    ],
    "relations": [
        {
            "dataType": "ConstellationRelation",
            "sourceConstellation": "76775983",
            "targetConstellation": "67934687",
            "sourceArkID": "http:\/\/n2t.net\/ark:\/99166\/w6b38htz",
            "targetArkID": "http:\/\/n2t.net\/ark:\/99166\/w6gn6pns",
            "targetEntityType": {
                "id": "698",
                "term": "corporateBody",
                "uri": "http:\/\/socialarchive.iath.virginia.edu\/control\/term#CorporateBody",
                "type": "entity_type"
            },
            "type": {
                "term": "mayBeSameAs",
                "type": "relation_type"
            },
            "content": "Naperville Public Library (Naperville, Ill.)"
        }
    ],
    "places": [
        {
            "dataType": "Place",
            "original": "Naperville Public Library",
            "type": {
                "id": "400242",
                "term": "Address",
                "uri": "http:\/\/socialarchive.iath.virginia.edu\/control\/term#Address",
                "type": "place_type"
            },
            "address": [
                {
                    "dataType": "AddressLine",
                    "text": "200 W Jefferson Ave",
                    "order": "0",
                    "type": {
                        "id": "400243",
                        "term": "Unspecified",
                        "uri": "http:\/\/socialarchive.iath.virginia.edu\/control\/term#Unspecified",
                        "type": "address_part"
                    },
                    "id": "76775989",
                    "version": "11230013"
                },
                {
                    "dataType": "AddressLine",
                    "text": "Naperville",
                    "order": "1",
                    "type": {
                        "id": "400243",
                        "term": "Unspecified",
                        "uri": "http:\/\/socialarchive.iath.virginia.edu\/control\/term#Unspecified",
                        "type": "address_part"
                    },
                    "id": "76775990",
                    "version": "11230013"
                },
                {
                    "dataType": "AddressLine",
                    "text": "US-IL",
                    "order": "2",
                    "type": {
                        "id": "400243",
                        "term": "Unspecified",
                        "uri": "http:\/\/socialarchive.iath.virginia.edu\/control\/term#Unspecified",
                        "type": "address_part"
                    },
                    "id": "76775991",
                    "version": "11230013"
                },
                {
                    "dataType": "AddressLine",
                    "text": "60540-5374",
                    "order": "3",
                    "type": {
                        "id": "400243",
                        "term": "Unspecified",
                        "uri": "http:\/\/socialarchive.iath.virginia.edu\/control\/term#Unspecified",
                        "type": "address_part"
                    },
                    "id": "76775992",
                    "version": "11230013"
                },
                {
                    "dataType": "AddressLine",
                    "text": "US",
                    "order": "4",
                    "type": {
                        "id": "400243",
                        "term": "Unspecified",
                        "uri": "http:\/\/socialarchive.iath.virginia.edu\/control\/term#Unspecified",
                        "type": "address_part"
                    },
                    "id": "76775993",
                    "version": "11230013"
                }
            ],
            "geoplace": {
                "id": "16119",
                "name": "Naperville Public Library",
                "latitude": "41.7636000",
                "longitude": "-88.1449000"
            },
            "confirmed": true,
            "id": "76775988",
            "version": "11230013"
        }
    ],
    "id": "76775983",
    "version": "11230016"
}