{
    "dataType": "Constellation",
    "ark": "http:\/\/n2t.net\/ark:\/99166\/w6vn51w3",
    "entityType": {
        "id": "698",
        "term": "corporateBody",
        "uri": "http:\/\/socialarchive.iath.virginia.edu\/control\/term#CorporateBody",
        "type": "entity_type"
    },
    "entityIDs": [
        {
            "dataType": "EntityId",
            "type": {
                "id": "703",
                "term": "MARCOrg",
                "type": "entityid_type"
            },
            "text": "OkU-C",
            "id": "76787635",
            "version": "11234269"
        },
        {
            "dataType": "EntityId",
            "type": {
                "id": "400255",
                "term": "OCLC ID",
                "type": "entityid_type",
                "description": "OCLC Numeric Identifier"
            },
            "text": "5477",
            "id": "76787636",
            "version": "11234269"
        }
    ],
    "maintenanceStatus": {
        "term": "revised"
    },
    "maintenanceAgency": "SNAC: Social Networks and Archival Context",
    "maintenanceEvents": [
        {
            "dataType": "MaintenanceEvent",
            "eventType": {
                "id": "704",
                "term": "revised",
                "type": "event_type"
            },
            "eventDateTime": "2016-11-22T11:48:11",
            "standardDateTime": "2016-11-22T11:48:11",
            "agentType": {
                "id": "400254",
                "term": "human",
                "type": "agent_type"
            },
            "agent": "System Service (system@localhost)",
            "eventDescription": "User published constellation"
        }
    ],
    "nameEntries": [
        {
            "dataType": "NameEntry",
            "original": "University of Oklahoma, Political Community Archives",
            "preferenceScore": "99",
            "components": [
                {
                    "dataType": "NameComponent",
                    "text": "University of Oklahoma, Political Community Archives",
                    "order": "0",
                    "type": {
                        "id": "400228",
                        "term": "Name",
                        "type": "name_component"
                    },
                    "id": "76787634",
                    "version": "11234269"
                }
            ],
            "id": "76787633",
            "version": "11234269"
        }
    ],
    "places": [
        {
            "dataType": "Place",
            "original": "University of Oklahoma, Political Community Archives",
            "type": {
                "id": "400242",
                "term": "Address",
                "uri": "http:\/\/socialarchive.iath.virginia.edu\/control\/term#Address",
                "type": "place_type"
            },
            "address": [
                {
                    "dataType": "AddressLine",
                    "text": "Burton Hall",
                    "order": "0",
                    "type": {
                        "id": "400243",
                        "term": "Unspecified",
                        "uri": "http:\/\/socialarchive.iath.virginia.edu\/control\/term#Unspecified",
                        "type": "address_part"
                    },
                    "id": "76787638",
                    "version": "11234269"
                },
                {
                    "dataType": "AddressLine",
                    "text": "610 Elm Ave",
                    "order": "1",
                    "type": {
                        "id": "400243",
                        "term": "Unspecified",
                        "uri": "http:\/\/socialarchive.iath.virginia.edu\/control\/term#Unspecified",
                        "type": "address_part"
                    },
                    "id": "76787639",
                    "version": "11234269"
                },
                {
                    "dataType": "AddressLine",
                    "text": "Norman",
                    "order": "2",
                    "type": {
                        "id": "400243",
                        "term": "Unspecified",
                        "uri": "http:\/\/socialarchive.iath.virginia.edu\/control\/term#Unspecified",
                        "type": "address_part"
                    },
                    "id": "76787640",
                    "version": "11234269"
                },
                {
                    "dataType": "AddressLine",
                    "text": "US-OK",
                    "order": "3",
                    "type": {
                        "id": "400243",
                        "term": "Unspecified",
                        "uri": "http:\/\/socialarchive.iath.virginia.edu\/control\/term#Unspecified",
                        "type": "address_part"
                    },
                    "id": "76787641",
                    "version": "11234269"
                },
                {
                    "dataType": "AddressLine",
                    "text": "73019-2081",
                    "order": "4",
                    "type": {
                        "id": "400243",
                        "term": "Unspecified",
                        "uri": "http:\/\/socialarchive.iath.virginia.edu\/control\/term#Unspecified",
                        "type": "address_part"
                    },
                    "id": "76787642",
                    "version": "11234269"
                },
                {
                    "dataType": "AddressLine",
                    "text": "US",
                    "order": "5",
                    "type": {
                        "id": "400243",
                        "term": "Unspecified",
                        "uri": "http:\/\/socialarchive.iath.virginia.edu\/control\/term#Unspecified",
                        "type": "address_part"
                    },
                    "id": "76787643",
                    "version": "11234269"
                }
            ],
            "geoplace": {
                "id": "16178",
                "name": "University of Oklahoma, Political Community Archives",
                "latitude": "35.1967050",
                "longitude": "-97.4427490"
            },
            "confirmed": true,
            "id": "76787637",
            "version": "11234269"
        }
    ],
    "id": "76787632",
    "version": "11234272"
}