{
    "dataType": "Constellation",
    "ark": "http:\/\/n2t.net\/ark:\/99166\/w6r60dd2",
    "entityType": {
        "id": "698",
        "term": "corporateBody",
        "uri": "http:\/\/socialarchive.iath.virginia.edu\/control\/term#CorporateBody",
        "type": "entity_type"
    },
    "entityIDs": [
        {
            "dataType": "EntityId",
            "type": {
                "id": "703",
                "term": "MARCOrg",
                "type": "entityid_type"
            },
            "text": "TMM",
            "id": "76786924",
            "version": "11234025"
        },
        {
            "dataType": "EntityId",
            "type": {
                "id": "400255",
                "term": "OCLC ID",
                "type": "entityid_type",
                "description": "OCLC Numeric Identifier"
            },
            "text": "2765",
            "id": "76786925",
            "version": "11234025"
        }
    ],
    "maintenanceStatus": {
        "term": "revised"
    },
    "maintenanceAgency": "SNAC: Social Networks and Archival Context",
    "maintenanceEvents": [
        {
            "dataType": "MaintenanceEvent",
            "eventType": {
                "id": "704",
                "term": "revised",
                "type": "event_type"
            },
            "eventDateTime": "2016-11-22T11:47:36",
            "standardDateTime": "2016-11-22T11:47:36",
            "agentType": {
                "id": "400254",
                "term": "human",
                "type": "agent_type"
            },
            "agent": "System Service (system@localhost)",
            "eventDescription": "User published constellation"
        }
    ],
    "nameEntries": [
        {
            "dataType": "NameEntry",
            "original": "University of Memphis, Ned R. McWherter Library",
            "preferenceScore": "99",
            "components": [
                {
                    "dataType": "NameComponent",
                    "text": "University of Memphis, Ned R. McWherter Library",
                    "order": "0",
                    "type": {
                        "id": "400228",
                        "term": "Name",
                        "type": "name_component"
                    },
                    "id": "76786923",
                    "version": "11234025"
                }
            ],
            "id": "76786922",
            "version": "11234025"
        }
    ],
    "places": [
        {
            "dataType": "Place",
            "original": "University of Memphis, Ned R. McWherter Library",
            "type": {
                "id": "400242",
                "term": "Address",
                "uri": "http:\/\/socialarchive.iath.virginia.edu\/control\/term#Address",
                "type": "place_type"
            },
            "address": [
                {
                    "dataType": "AddressLine",
                    "text": "3785 Norriswood Ave",
                    "order": "0",
                    "type": {
                        "id": "400243",
                        "term": "Unspecified",
                        "uri": "http:\/\/socialarchive.iath.virginia.edu\/control\/term#Unspecified",
                        "type": "address_part"
                    },
                    "id": "76786927",
                    "version": "11234025"
                },
                {
                    "dataType": "AddressLine",
                    "text": "Memphis",
                    "order": "1",
                    "type": {
                        "id": "400243",
                        "term": "Unspecified",
                        "uri": "http:\/\/socialarchive.iath.virginia.edu\/control\/term#Unspecified",
                        "type": "address_part"
                    },
                    "id": "76786928",
                    "version": "11234025"
                },
                {
                    "dataType": "AddressLine",
                    "text": "US-TN",
                    "order": "2",
                    "type": {
                        "id": "400243",
                        "term": "Unspecified",
                        "uri": "http:\/\/socialarchive.iath.virginia.edu\/control\/term#Unspecified",
                        "type": "address_part"
                    },
                    "id": "76786929",
                    "version": "11234025"
                },
                {
                    "dataType": "AddressLine",
                    "text": "38152",
                    "order": "3",
                    "type": {
                        "id": "400243",
                        "term": "Unspecified",
                        "uri": "http:\/\/socialarchive.iath.virginia.edu\/control\/term#Unspecified",
                        "type": "address_part"
                    },
                    "id": "76786930",
                    "version": "11234025"
                },
                {
                    "dataType": "AddressLine",
                    "text": "US",
                    "order": "4",
                    "type": {
                        "id": "400243",
                        "term": "Unspecified",
                        "uri": "http:\/\/socialarchive.iath.virginia.edu\/control\/term#Unspecified",
                        "type": "address_part"
                    },
                    "id": "76786931",
                    "version": "11234025"
                }
            ],
            "geoplace": {
                "id": "16566",
                "name": "University of Memphis, Ned R. McWherter Library",
                "latitude": "35.1199837",
                "longitude": "-89.9358368"
            },
            "confirmed": true,
            "id": "76786926",
            "version": "11234025"
        }
    ],
    "id": "76786921",
    "version": "11234028"
}