<?xml version="1.0" encoding="UTF-8"?>
<eac-cpf xmlns="urn:isbn:1-931666-33-4" xmlns:xlink="http://www.w3.org/1999/xlink" xmlns:snac="http://socialarchive.iath.virginia.edu/">
  <control>
    <recordId>http://n2t.net/ark:/99166/w6s001f6</recordId>
    <maintenanceStatus>revised</maintenanceStatus>
    <maintenanceAgency>
      <agencyName>
                SNAC: Social Networks and Archival Context
            </agencyName>
    </maintenanceAgency>
    <maintenanceHistory>
      <maintenanceEvent>
        <eventType>revised</eventType>
        <eventDateTime standardDateTime="2016-11-22T11:24:45">2016-11-22T11:24:45</eventDateTime>
        <agentType>human</agentType>
        <agent>System Service (system@localhost)</agent>
        <eventDescription>User published constellation</eventDescription>
      </maintenanceEvent>
      <maintenanceEvent>
        <eventType>created</eventType>
        <eventDateTime standardDateTime="2017-07-21">2017-07-21</eventDateTime>
        <agentType>machine</agentType>
        <agent>SNAC EAC-CPF Serializer</agent>
        <eventDescription>SNAC Identity Constellation serialized to EAC-CPF</eventDescription>
      </maintenanceEvent>
    </maintenanceHistory>
    <sources>
                    </sources>
  </control>
  <cpfDescription>
    <identity>
      <entityType>corporateBody</entityType>
      <entityId>DABA</entityId>
      <entityId>39275</entityId>
      <nameEntry snac:preferenceScore="99">
        <part>American Bankers Association</part>
      </nameEntry>
    </identity>
    <description>
      <place localType="http://socialarchive.iath.virginia.edu/control/term#Address">
        <placeEntry certaintyScore="" vocabularySource="" latitude="38.8904000" longitude="-77.0320000" administrationCode="" countryCode="">American Bankers Association
                </placeEntry>
        <address>
          <addressLine localType="http://socialarchive.iath.virginia.edu/control/term#Unspecified">Ctr For Banking Info</addressLine>
          <addressLine localType="http://socialarchive.iath.virginia.edu/control/term#Unspecified">1120 Connecticut Ave Nw</addressLine>
          <addressLine localType="http://socialarchive.iath.virginia.edu/control/term#Unspecified">Washington</addressLine>
          <addressLine localType="http://socialarchive.iath.virginia.edu/control/term#Unspecified">US-DC</addressLine>
          <addressLine localType="http://socialarchive.iath.virginia.edu/control/term#Unspecified">20036</addressLine>
          <addressLine localType="http://socialarchive.iath.virginia.edu/control/term#Unspecified">US</addressLine>
        </address>
      </place>
    </description>
    <relations>
      <cpfRelation xlink:type="simple" xlink:role="http://socialarchive.iath.virginia.edu/control/term#CorporateBody" xlink:arcrole="mayBeSameAs" xlink:href="http://n2t.net/ark:/99166/w6b32w5q">
        <relationEntry>American Bankers Association.</relationEntry>
      </cpfRelation>
    </relations>
  </cpfDescription>
</eac-cpf>
